Workbook

Sheet Instructions
A1: MS Excel Practical Exam
A2: Total Questions: 30
A3: Difficulty Level: Medium
A4: Syllabus: Formulas, Logical Functions, Lookups, INDEX-MATCH, Pivot Tables & Charts, Data Analysis
A5: Attempt all questions using appropriate Excel tools/functions.

Sheet Sales_Data
A1: Order_ID | B1: Region | C1: Salesperson | D1: Product | E1: Quantity | F1: Unit_Price | G1: Sales_Date
A2: 301 | B2: North | C2: Amit | D2: Laptop | E2: 2 | F2: 45000 | G2: 05-01-2025
A3: 302 | B3: South | C3: Riya | D3: Mobile | E3: 5 | F3: 15000 | G3: 07-01-2025
A4: 303 | B4: East | C4: Kunal | D4: Tablet | E4: 3 | F4: 18000 | G4: 10-01-2025
A5: 304 | B5: West | C5: Neha | D5: Laptop | E5: 1 | F5: 45000 | G5: 12-01-2025
A6: 305 | B6: North | C6: Amit | D6: Mobile | E6: 4 | F6: 15000 | G6: 15-01-2025
A7: 306 | B7: South | C7: Riya | D7: Laptop | E7: 2 | F7: 45000 | G7: 18-01-2025

Sheet Product_Master
A1: Product | B1: Category | C1: GST_%
A2: Laptop | B2: Electronics | C2: 18
A3: Mobile | B3: Electronics | C3: 12
A4: Tablet | B4: Electronics | C4: 12

Sheet Student_Marks
A1: Student_ID | B1: Name | C1: Maths | D1: Statistics | E1: Excel | F1: Attendance_%
A2: 1 | B2: Rahul | C2: 78 | D2: 82 | E2: 85 | F2: 92
A3: 2 | B3: Sneha | C3: 88 | D3: 91 | E3: 90 | F3: 96
A4: 3 | B4: Arjun | C4: 65 | D4: 70 | E4: 72 | F4: 85
A5: 4 | B5: Pooja | C5: 92 | D5: 89 | E5: 94 | F5: 98
A6: 5 | B6: Vikas | C6: 55 | D6: 60 | E6: 58 | F6: 80

Sheet Questions
A1: 1. Calculate Total Sales for each order (Quantity × Unit_Price). | J1: 2
A2: 2. Calculate GST Amount using VLOOKUP from Product_Master. | J2: 2
A3: 3. Find Final Amount payable (Total Sales + GST). | J3: 2
A4: 4. Find Grand Total of Final Amount. | J4: 2
A5: 5. Count total number of orders using COUNTA. | J5: 2
A6: 6. Find Region-wise total sales using SUMIF. | J6: 2
A7: 7. Use IF to classify Quantity as High (>3) or Low (<=3). | J7: 2
A8: 8. Find the maximum and minimum Final Amount. | J8: 2
A9: 9. Extract month name from Sales_Date. | J9: 2
A10: 10. Sort Sales_Data by Final Amount (Descending). | J10: 2
A11: 11. Use INDEX-MATCH to fetch Product Category. | J11: 2
A12: 12. Calculate average marks of each student. | J12: 2
... A30: 29. Freeze top row in Sales_Data sheet. | J30: 2
J32: =SUM(J1:J30) -> 60

Sheet Answer-3
A1: Order_ID | B1: Quantity | C1: Unit_Price | D1: Total Salse | E1: Product | F1: GST_% | G1: GST Amount | H1: Final Amount | I1: Region | J1: Quantity_c
A2: 301 | B2: 2 | C2: 45000 | D2: 90000 | E2: Laptop | F2: 18 | G2: 16200 | H2: 106200 | I2: North | J2: Low
A3: 306 | B3: 2 | C3: 45000 | D3: 90000 | E3: Laptop | F3: 18 | G3: 16200 | H3: 106200 | I3: South | J3: Low
A4: 302 | B4: 5 | C4: 15000 | D4: 75000 | E4: Mobile | F4: 12 | G4: 9000 | H4: 84000 | I4: South | J4: Low
A5: 305 | B5: 4 | C5: 15000 | D5: 60000 | E5: Mobile | F5: 12 | G5: 7200 | H5: 67200 | I5: North | J5: Low
A6: 303 | B6: 3 | C6: 18000 | D6: 54000 | E6: Tablet | F6: 12 | G6: 6480 | H6: 60480 | I6: East | J6: High
A7: 304 | B7: 1 | C7: 45000 | D7: 45000 | E7: Laptop | F7: 18 | G7: 8100 | H7: 53100 | I7: West | J7: High
A13: Order_ID | B13: Quantity | C13: Unit_Price | D13: Total Salse | E13: Product | F13: GST_% | G13: GST Amount | H13: Final Amount | I13: Region | J13: Quantity_c
A14: 301 | B14: 2 | C14: 45000 | D14: 90000 | E14: Laptop | F14: 18 | G14: 16200 | H14: 106200 | I14: North | J14: Low
A15: 306 | B15: 2 | C15: 45000 | D15: 90000 | E15: Laptop | F15: 18 | G15: 16200 | H15: 106200 | I15: South | J15: Low
A16: 302 | B16: 5 | C16: 15000 | D16: 75000 | E16: Mobile | F16: 12 | G16: 9000 | H16: 84000 | I16: South | J16: Low
A17: 305 | B17: 4 | C17: 15000 | D17: 60000 | E17: Mobile | F17: 12 | G17: 7200 | H17: 67200 | I17: North | J17: Low
A18: 303 | B18: 3 | C18: 18000 | D18: 54000 | E18: Tablet | F18: 12 | G18: 6480 | H18: 60480 | I18: East | J18: High
A19: 304 | B19: 1 | C19: 45000 | D19: 45000 | E19: Laptop | F19: 18 | G19: 8100 | H19: 53100 | I19: West | J19: High

Sheet Answer
A1: Order_ID | B1: Quantity | C1: Unit_Price | D1: Total Salse | E1: Product | F1: GST_% | G1: GST Amount | H1: Final Amount | I1: Region | J1: Quantity_c | K1: Month | L1: Product2 | M1: Name | N1: Get Name | O1: New Unit Price
A2: 301 | B2: =VLOOKUP(A2,Sales_Data!$A$1:$G$7,5,0) -> 2 | C2: =VLOOKUP(A2,Sales_Data!$A$1:$G$7,6,0) -> 45000 | D2: =B2*C2 -> 90000 | E2: =VLOOKUP(A2,Sales_Data!$A$1:$G$7,4,0) -> Laptop | F2: =VLOOKUP(E2,Product_Master!$A$1:$C$4,3,0) -> 18 | G2: =F2*D2/100 -> 16200 | H2: =G2+D2 -> 106200 | I2: =VLOOKUP(A2,Sales_Data!$A$1:$G$7,2,0) -> North | J2: =IF(Answer!B2>3,"High","Low") -> Low | K2: =TRIM(Sales_Data!G2:G7) -> 05-01-2025 | L2: =INDEX(Product_Master!$A$1:$C$4,MATCH(E2,Product_Master!$A$1:$A$4,0),1) -> Laptop | M2: =VLOOKUP(A2,Sales_Data!$A$1:$G$7,3,0) -> Amit | N2: =LEFT(M2,2) -> Am | O2: =ROUND(C2,2) -> 45000
A3: 302 | B3: =VLOOKUP(A3,Sales_Data!$A$1:$G$7,5,0) -> 5 | C3: =VLOOKUP(A3,Sales_Data!$A$1:$G$7,6,0) -> 15000 | D3: =B3*C3 -> 75000 | E3: =VLOOKUP(A3,Sales_Data!$A$1:$G$7,4,0) -> Mobile | F3: =VLOOKUP(E3,Product_Master!$A$1:$C$4,3,0) -> 12 | G3: =F3*D3/100 -> 9000 | H3: =G3+D3 -> 84000 | I3: =VLOOKUP(A3,Sales_Data!$A$1:$G$7,2,0) -> South | J3: =IF(Answer!B3>3,"High","Low") -> High | K3: =TRIM(Sales_Data!G3:G8) -> 07-01-2025 | L3: =INDEX(Product_Master!$A$1:$C$4,MATCH(E3,Product_Master!$A$1:$A$4,0),1) -> Mobile | M3: =VLOOKUP(A3,Sales_Data!$A$1:$G$7,3,0) -> Riya | N3: =LEFT(M3,2) -> Ri | O3: =ROUND(C3,2) -> 15000
A4: 303 | B4: =VLOOKUP(A4,Sales_Data!$A$1:$G$7,5,0) -> 3 | C4: =VLOOKUP(A4,Sales_Data!$A$1:$G$7,6,0) -> 18000 | D4: =B4*C4 -> 54000 | E4: =VLOOKUP(A4,Sales_Data!$A$1:$G$7,4,0) -> Tablet | F4: =VLOOKUP(E4,Product_Master!$A$1:$C$4,3,0) -> 12 | G4: =F4*D4/100 -> 6480 | H4: =G4+D4 -> 60480 | I4: =VLOOKUP(A4,Sales_Data!$A$1:$G$7,2,0) -> East | J4: =IF(Answer!B4>3,"High","Low") -> Low | K4: =TRIM(Sales_Data!G4:G9) -> 10-01-2025 | L4: =INDEX(Product_Master!$A$1:$C$4,MATCH(E4,Product_Master!$A$1:$A$4,0),1) -> Tablet | M4: =VLOOKUP(A4,Sales_Data!$A$1:$G$7,3,0) -> Kunal | N4: =LEFT(M4,2) -> Ku | O4: =ROUND(C4,2) -> 18000 | S4: Max Final Amount | T4: =MAX(H2:H6) -> 106200
A5: 305 | B5: =VLOOKUP(A5,Sales_Data!$A$1:$G$7,5,0) -> 4 | C5: =VLOOKUP(A5,Sales_Data!$A$1:$G$7,6,0) -> 15000 | D5: =B5*C5 -> 60000 | E5: =VLOOKUP(A5,Sales_Data!$A$1:$G$7,4,0) -> Mobile | F5: =VLOOKUP(E5,Product_Master!$A$1:$C$4,3,0) -> 12 | G5: =F5*D5/100 -> 7200 | H5: =G5+D5 -> 67200 | I5: =VLOOKUP(A5,Sales_Data!$A$1:$G$7,2,0) -> North | J5: =IF(Answer!B6>3,"High","Low") -> Low | K5: =TRIM(Sales_Data!G6:G11) -> #VALUE! | L5: =INDEX(Product_Master!$A$1:$C$4,MATCH(E5,Product_Master!$A$1:$A$4,0),1) -> Mobile | M5: =VLOOKUP(A5,Sales_Data!$A$1:$G$7,3,0) -> Amit | N5: =LEFT(M5,2) -> Am | O5: =ROUND(C5,2) -> 15000 | S5: Min Final Amount | T5: =MIN(H2:H6) -> 60480
A6: 306 | B6: =VLOOKUP(A6,Sales_Data!$A$1:$G$7,5,0) -> 2 | C6: =VLOOKUP(A6,Sales_Data!$A$1:$G$7,6,0) -> 45000 | D6: =B6*C6 -> 90000 | E6: =VLOOKUP(A6,Sales_Data!$A$1:$G$7,4,0) -> Laptop | F6: =VLOOKUP(E6,Product_Master!$A$1:$C$4,3,0) -> 18 | G6: =F6*D6/100 -> 16200 | H6: =G6+D6 -> 106200 | I6: =VLOOKUP(A6,Sales_Data!$A$1:$G$7,2,0) -> South | J6: =IF(Answer!B7>3,"High","Low") -> Low | K6: =TRIM(Sales_Data!G7:G12) -> #VALUE! | L6: =INDEX(Product_Master!$A$1:$C$4,MATCH(E6,Product_Master!$A$1:$A$4,0),1) -> Laptop | M6: =VLOOKUP(A6,Sales_Data!$A$1:$G$7,3,0) -> Riya | N6: =LEFT(M6,2) -> Ri | O6: =ROUND(C6,2) -> 45000 | S6: Total Final Amount | T6: =SUM(H2:H6) -> 424080
S7: Number of Orders | T7: =COUNTA(A2:A6) -> 5
A10: Region | B10: Total
A11: North | B11: =SUMIF($I$2:$I$6,"North",H2:H6) -> 173400 | S11: Number of laptops order in north | T11: =COUNTIFS(Answer!I2:I6,"North") -> 2
A12: South | B12: =SUMIF($I$2:$I$6,"North",H3:H8) -> 190200
A13: East | B13: =SUMIF($I$2:$I$6,"North",H4:H9) -> 60480
A14: West | B14: =SUMIF($I$2:$I$6,"North",H5:H10) -> 67200
A17: Order_ID | B17: Quantity | C17: Unit_Price | D17: Total Salse | E17: Product | F17: GST_% | G17: GST Amount | H17: Final Amount | I17: Region | J17: Quantity_c
A18: 301 | B18: =VLOOKUP(A18,Sales_Data!$A$1:$G$7,5,0) -> 2 | C18: =VLOOKUP(A18,Sales_Data!$A$1:$G$7,6,0) -> 45000 | D18: =B18*C18 -> 90000 | E18: =VLOOKUP(A18,Sales_Data!$A$1:$G$7,4,0) -> Laptop | F18: =VLOOKUP(E18,Product_Master!$A$1:$C$4,3,0) -> 18 | G18: =F18*D18/100 -> 16200 | H18: =G18+D18 -> 106200 | I18: =VLOOKUP(A18,Sales_Data!$A$1:$G$7,2,0) -> North | J18: =IF(Answer!B18>3,"High","Low") -> Low
A19: 306 | B19: =VLOOKUP(A19,Sales_Data!$A$1:$G$7,5,0) -> 2 | C19: =VLOOKUP(A19,Sales_Data!$A$1:$G$7,6,0) -> 45000 | D19: =B19*C19 -> 90000 | E19: =VLOOKUP(A19,Sales_Data!$A$1:$G$7,4,0) -> Laptop | F19: =VLOOKUP(E19,Product_Master!$A$1:$C$4,3,0) -> 18 | G19: =F19*D19/100 -> 16200 | H19: =G19+D19 -> 106200 | I19: =VLOOKUP(A19,Sales_Data!$A$1:$G$7,2,0) -> South | J19: =IF(Answer!B23>3,"High","Low") -> Low
A20: 302 | B20: =VLOOKUP(A20,Sales_Data!$A$1:$G$7,5,0) -> 5 | C20: =VLOOKUP(A20,Sales_Data!$A$1:$G$7,6,0) -> 15000 | D20: =B20*C20 -> 75000 | E20: =VLOOKUP(A20,Sales_Data!$A$1:$G$7,4,0) -> Mobile | F20: =VLOOKUP(E20,Product_Master!$A$1:$C$4,3,0) -> 12 | G20: =F20*D20/100 -> 9000 | H20: =G20+D20 -> 84000 | I20: =VLOOKUP(A20,Sales_Data!$A$1:$G$7,2,0) -> South | J20: =IF(Answer!B19>3,"High","Low") -> Low
A21: 305 | B21: =VLOOKUP(A21,Sales_Data!$A$1:$G$7,5,0) -> 4 | C21: =VLOOKUP(A21,Sales_Data!$A$1:$G$7,6,0) -> 15000 | D21: =B21*C21 -> 60000 | E21: =VLOOKUP(A21,Sales_Data!$A$1:$G$7,4,0) -> Mobile | F21: =VLOOKUP(E21,Product_Master!$A$1:$C$4,3,0) -> 12 | G21: =F21*D21/100 -> 7200 | H21: =G21+D21 -> 67200 | I21: =VLOOKUP(A21,Sales_Data!$A$1:$G$7,2,0) -> North | J21: =IF(Answer!B22>3,"High","Low") -> Low
A22: 303 | B22: =VLOOKUP(A22,Sales_Data!$A$1:$G$7,5,0) -> 3 | C22: =VLOOKUP(A22,Sales_Data!$A$1:$G$7,6,0) -> 18000 | D22: =B22*C22 -> 54000 | E22: =VLOOKUP(A22,Sales_Data!$A$1:$G$7,4,0) -> Tablet | F22: =VLOOKUP(E22,Product_Master!$A$1:$C$4,3,0) -> 12 | G22: =F22*D22/100 -> 6480 | H22: =G22+D22 -> 60480 | I22: =VLOOKUP(A22,Sales_Data!$A$1:$G$7,2,0) -> East | J22: =IF(Answer!B20>3,"High","Low") -> High
A23: 304 | B23: =VLOOKUP(A23,Sales_Data!$A$1:$G$7,5,0) -> 1 | C23: =VLOOKUP(A23,Sales_Data!$A$1:$G$7,6,0) -> 45000 | D23: =B23*C23 -> 45000 | E23: =VLOOKUP(A23,Sales_Data!$A$1:$G$7,4,0) -> Laptop | F23: =VLOOKUP(E23,Product_Master!$A$1:$C$4,3,0) -> 18 | G23: =F23*D23/100 -> 8100 | H23: =G23+D23 -> 53100 | I23: =VLOOKUP(A23,Sales_Data!$A$1:$G$7,2,0) -> West | J23: =IF(Answer!B21>3,"High","Low") -> High

Sheet Answer-2
A1: Student_ID | B1: Name | C1: Maths | D1: Statistics | E1: Excel | F1: Attendance_% | G1: Classify | H1: Combine
A2: 1 | B2: Rahul | C2: 78 | D2: 82 | E2: 85 | F2: 92 | G2: =IF(F2>=85,"Eligible","Not Eligible") -> Eligible | H2: =_xlfn.CONCAT(A2,B2) -> 1Rahul
A3: 2 | B3: Sneha | C3: 88 | D3: 91 | E3: 90 | F3: 96 | G3: =IF(F3>=85,"Eligible","Not Eligible") -> Eligible | H3: =_xlfn.CONCAT(A3,B3) -> 2Sneha
A4: 3 | B4: Arjun | C4: 65 | D4: 70 | E4: 72 | F4: 85 | G4: =IF(F4>=85,"Eligible","Not Eligible") -> Eligible | H4: =_xlfn.CONCAT(A4,B4) -> 3Arjun
A5: 4 | B5: Pooja | C5: 92 | D5: 89 | E5: 94 | F5: 98 | G5: =IF(F5>=85,"Eligible","Not Eligible") -> Eligible | H5: =_xlfn.CONCAT(A5,B5) -> 4Pooja
A6: 5 | B6: Vikas | C6: 55 | D6: 60 | E6: 58 | F6: 80 | G6: =IF(F6>=85,"Eligible","Not Eligible") -> Not Eligible | H6: =_xlfn.CONCAT(A6,B6) -> 5Vikas
J8: Names | K8: Marks
J9: Rahul | K9: =SUM(C2:E2)/3 -> 81.666667
J10: Sneha | K10: =SUM(C3:E3)/3 -> 89.666667 | N10: Topper | O10: Mark
J11: Arjun | K11: =SUM(C4:E4)/3 -> 69 | N11: =_xlfn.XLOOKUP(O11,K9:K13,J9:J13) -> Pooja | O11: =MAX(K9:K13) -> 91.666667
J12: Pooja | K12: =SUM(C5:E5)/3 -> 91.666667
J13: Vikas | K13: =SUM(C6:E6)/3 -> 57.666667
D14: Median of stats | E14: =MEDIAN(D2:D6) -> 82
D15: Std of excel | E15: =_xlfn.STDEV.P(E2:E6) -> 13.181806
J17: Students whose attendance is over 90
J18: =COUNTIF(F2:F6, ">90") -> 3

Sheet Pivot Table
K8: Row Labels | L8: Sum of Marks
B9: Row Labels | C9: Sum of Total Salse | K9: Arjun | L9: 69
B10: Laptop | C10: 225000 | K10: Pooja | L10: 91.666667
B11: Mobile | C11: 135000 | K11: Rahul | L11: 81.666667
B12: Tablet | C12: 54000 | K12: Sneha | L12: 89.666667
B13: Grand Total | C13: 414000 | K13: Vikas | L13: 57.666667
K14: Grand Total | L14: 389.66667
B16: Row Labels | C16: Sum of Total Salse | F16: Row Labels | G16: Sum of Total Salse
B17: East | C17: 54000 | F17: Laptop | G17: 225000
B18: North | C18: 150000 | F18: Mobile | G18: 135000
B19: South | C19: 165000 | F19: Tablet | G19: 54000
B20: West | C20: 45000 | F20: Grand Total | G20: 414000
B21: Grand Total | C21: 414000

Sheet Dashboard
