Workbook

Sheet Instructions
A1: MS Excel Practical Exam
A2: Total Questions: 30
A3: Difficulty Level: Medium
A4: Syllabus: Formulas, Logical Functions, Lookups, INDEX-MATCH, Pivot Tables & Charts, Data Analysis
A5: Attempt all questions using appropriate Excel tools/functions.

Sheet Sales_Data
A1: Order_ID | B1: Region | C1: Salesperson | D1: Product | E1: Quantity | F1: Unit_Price | G1: Sales_Date
A2: 301 | B2: North | C2: Amit | D2: Laptop | E2: 2 | F2: 45000 | G2: 05-01-2025
A3: 302 | B3: South | C3: Riya | D3: Mobile | E3: 5 | F3: 15000 | G3: 07-01-2025
A4: 303 | B4: East | C4: Kunal | D4: Tablet | E4: 3 | F4: 18000 | G4: 10-01-2025
A5: 304 | B5: West | C5: Neha | D5: Laptop | E5: 1 | F5: 45000 | G5: 12-01-2025
A6: 305 | B6: North | C6: Amit | D6: Mobile | E6: 4 | F6: 15000 | G6: 15-01-2025
A7: 306 | B7: South | C7: Riya | D7: Laptop | E7: 2 | F7: 45000 | G7: 18-01-2025

Sheet Product_Master
A1: Product | B1: Category | C1: GST_%
A2: Laptop | B2: Electronics | C2: 18
A3: Mobile | B3: Electronics | C3: 12
A4: Tablet | B4: Electronics | C4: 12

Sheet Student_Marks
A1: Student_ID | B1: Name | C1: Maths | D1: Statistics | E1: Excel | F1: Attendance_%
A2: 1 | B2: Rahul | C2: 78 | D2: 82 | E2: 85 | F2: 92
A3: 2 | B3: Sneha | C3: 88 | D3: 91 | E3: 90 | F3: 96
A4: 3 | B4: Arjun | C4: 65 | D4: 70 | E4: 72 | F4: 85
A5: 4 | B5: Pooja | C5: 92 | D5: 89 | E5: 94 | F5: 98
A6: 5 | B6: Vikas | C6: 55 | D6: 60 | E6: 58 | F6: 80

Sheet Questions
A1: 1. Calculate Total Sales for each order (Quantity × Unit_Price). | J1: 2
A2: 2. Calculate GST Amount using VLOOKUP from Product_Master. | J2: 2
A3: 3. Find Final Amount payable (Total Sales + GST). | J3: 2
A4: 4. Find Grand Total of Final Amount. | J4: 2
A5: 5. Count total number of orders using COUNTA. | J5: 2
A6: 6. Find Region-wise total sales using SUMIF. | J6: 2
A7: 7. Use IF to classify Quantity as High (>3) or Low (<=3). | J7: 2
A8: 8. Find the maximum and minimum Final Amount. | J8: 2
A9: 9. Extract month name from Sales_Date. | J9: 2
A10: 10. Sort Sales_Data by Final Amount (Descending). | J10: 2
A11: 11. Use INDEX-MATCH to fetch Product Category. | J11: 2
A12: 12. Calculate average marks of each student. | J12: 2
... A30: 30. Protect the Student_Marks sheet. | J30: 2
J32: =SUM(J1:J30) -> 60

Sheet Answer
A1: Order_ID | B1: Quantity | C1: Unit_Price | D1: Total Salse | E1: Product | F1: GST_% | G1: GST Amount | H1: Final Amount | I1: Region | J1: Quantity_c | K1: Month | L1: Product
A2: 301 | B2: =VLOOKUP(A2,Sales_Data!$A$1:$G$7,5,0) -> 2 | C2: =VLOOKUP(A2,Sales_Data!$A$1:$G$7,6,0) -> 45000 | D2: =B2*C2 -> 90000 | E2: =VLOOKUP(A2,Sales_Data!$A$1:$G$7,4,0) -> Laptop | F2: =VLOOKUP(E2,Product_Master!$A$1:$C$4,3,0) -> 18 | G2: =F2*D2/100 -> 16200 | H2: =G2+D2 -> 106200 | I2: =VLOOKUP(A2,Sales_Data!$A$1:$G$7,2,0) -> North | J2: =IF(Answer!B2>3,"High","Low") -> Low | K2: =TRIM(Sales_Data!G2:G7) -> 05-01-2025 | L2: =INDEX(Product_Master!$A$1:$C$4,MATCH(E2,Product_Master!$A$1:$A$4,0),1) -> Laptop
A3: 302 | B3: =VLOOKUP(A3,Sales_Data!$A$1:$G$7,5,0) -> 5 | C3: =VLOOKUP(A3,Sales_Data!$A$1:$G$7,6,0) -> 15000 | D3: =B3*C3 -> 75000 | E3: =VLOOKUP(A3,Sales_Data!$A$1:$G$7,4,0) -> Mobile | F3: =VLOOKUP(E3,Product_Master!$A$1:$C$4,3,0) -> 12 | G3: =F3*D3/100 -> 9000 | H3: =G3+D3 -> 84000 | I3: =VLOOKUP(A3,Sales_Data!$A$1:$G$7,2,0) -> South | J3: =IF(Answer!B3>3,"High","Low") -> High | K3: =TRIM(Sales_Data!G3:G8) -> 07-01-2025 | L3: =INDEX(Product_Master!$A$1:$C$4,MATCH(E3,Product_Master!$A$1:$A$4,0),1) -> Mobile
A4: 303 | B4: =VLOOKUP(A4,Sales_Data!$A$1:$G$7,5,0) -> 3 | C4: =VLOOKUP(A4,Sales_Data!$A$1:$G$7,6,0) -> 18000 | D4: =B4*C4 -> 54000 | E4: =VLOOKUP(A4,Sales_Data!$A$1:$G$7,4,0) -> Tablet | F4: =VLOOKUP(E4,Product_Master!$A$1:$C$4,3,0) -> 12 | G4: =F4*D4/100 -> 6480 | H4: =G4+D4 -> 60480 | I4: =VLOOKUP(A4,Sales_Data!$A$1:$G$7,2,0) -> East | J4: =IF(Answer!B4>3,"High","Low") -> Low | K4: =TRIM(Sales_Data!G4:G9) -> 10-01-2025 | L4: =INDEX(Product_Master!$A$1:$C$4,MATCH(E4,Product_Master!$A$1:$A$4,0),1) -> Tablet | P4: Max Final Amount | Q4: =MAX(H2:H7) -> 106200
A5: 304 | B5: =VLOOKUP(A5,Sales_Data!$A$1:$G$7,5,0) -> 1 | C5: =VLOOKUP(A5,Sales_Data!$A$1:$G$7,6,0) -> 45000 | D5: =B5*C5 -> 45000 | E5: =VLOOKUP(A5,Sales_Data!$A$1:$G$7,4,0) -> Laptop | F5: =VLOOKUP(E5,Product_Master!$A$1:$C$4,3,0) -> 18 | G5: =F5*D5/100 -> 8100 | H5: =G5+D5 -> 53100 | I5: =VLOOKUP(A5,Sales_Data!$A$1:$G$7,2,0) -> West | J5: =IF(Answer!B5>3,"High","Low") -> Low | K5: =TRIM(Sales_Data!G5:G10) -> 12-01-2025 | L5: =INDEX(Product_Master!$A$1:$C$4,MATCH(E5,Product_Master!$A$1:$A$4,0),1) -> Laptop | P5: Min Final Amount | Q5: =MIN(H2:H7) -> 53100
A6: 305 | B6: =VLOOKUP(A6,Sales_Data!$A$1:$G$7,5,0) -> 4 | C6: =VLOOKUP(A6,Sales_Data!$A$1:$G$7,6,0) -> 15000 | D6: =B6*C6 -> 60000 | E6: =VLOOKUP(A6,Sales_Data!$A$1:$G$7,4,0) -> Mobile | F6: =VLOOKUP(E6,Product_Master!$A$1:$C$4,3,0) -> 12 | G6: =F6*D6/100 -> 7200 | H6: =G6+D6 -> 67200 | I6: =VLOOKUP(A6,Sales_Data!$A$1:$G$7,2,0) -> North | J6: =IF(Answer!B6>3,"High","Low") -> High | K6: =TRIM(Sales_Data!G6:G11) -> 15-01-2025 | L6: =INDEX(Product_Master!$A$1:$C$4,MATCH(E6,Product_Master!$A$1:$A$4,0),1) -> Mobile | P6: Total Final Amount | Q6: =SUM(H2:H7) -> 477180
A7: 306 | B7: =VLOOKUP(A7,Sales_Data!$A$1:$G$7,5,0) -> 2 | C7: =VLOOKUP(A7,Sales_Data!$A$1:$G$7,6,0) -> 45000 | D7: =B7*C7 -> 90000 | E7: =VLOOKUP(A7,Sales_Data!$A$1:$G$7,4,0) -> Laptop | F7: =VLOOKUP(E7,Product_Master!$A$1:$C$4,3,0) -> 18 | G7: =F7*D7/100 -> 16200 | H7: =G7+D7 -> 106200 | I7: =VLOOKUP(A7,Sales_Data!$A$1:$G$7,2,0) -> South | J7: =IF(Answer!B7>3,"High","Low") -> Low | K7: =TRIM(Sales_Data!G7:G12) -> 18-01-2025 | L7: =INDEX(Product_Master!$A$1:$C$4,MATCH(E7,Product_Master!$A$1:$A$4,0),1) -> Laptop | P7: Number of Orders | Q7: =COUNTA(A2:A7) -> 6
A10: Region | B10: Total
A11: North | B11: =SUMIF(I2:I7,"North",H2:H7) -> 173400
A12: South | B12: =SUMIF(I3:I8,"North",H3:H8) -> 67200
A13: East | B13: =SUMIF(I4:I9,"North",H4:H9) -> 67200
A14: West | B14: =SUMIF(I5:I10,"North",H5:H10) -> 67200
A17: Order_ID | B17: Quantity | C17: Unit_Price | D17: Total Salse | E17: Product | F17: GST_% | G17: GST Amount | H17: Final Amount | I17: Region | J17: Quantity_c
A18: 301 | B18: =VLOOKUP(A18,Sales_Data!$A$1:$G$7,5,0) -> 2 | C18: =VLOOKUP(A18,Sales_Data!$A$1:$G$7,6,0) -> 45000 | D18: =B18*C18 -> 90000 | E18: =VLOOKUP(A18,Sales_Data!$A$1:$G$7,4,0) -> Laptop | F18: =VLOOKUP(E18,Product_Master!$A$1:$C$4,3,0) -> 18 | G18: =F18*D18/100 -> 16200 | H18: =G18+D18 -> 106200 | I18: =VLOOKUP(A18,Sales_Data!$A$1:$G$7,2,0) -> North | J18: =IF(Answer!B18>3,"High","Low") -> Low
A19: 306 | B19: =VLOOKUP(A19,Sales_Data!$A$1:$G$7,5,0) -> 2 | C19: =VLOOKUP(A19,Sales_Data!$A$1:$G$7,6,0) -> 45000 | D19: =B19*C19 -> 90000 | E19: =VLOOKUP(A19,Sales_Data!$A$1:$G$7,4,0) -> Laptop | F19: =VLOOKUP(E19,Product_Master!$A$1:$C$4,3,0) -> 18 | G19: =F19*D19/100 -> 16200 | H19: =G19+D19 -> 106200 | I19: =VLOOKUP(A19,Sales_Data!$A$1:$G$7,2,0) -> South | J19: =IF(Answer!B23>3,"High","Low") -> Low
A20: 302 | B20: =VLOOKUP(A20,Sales_Data!$A$1:$G$7,5,0) -> 5 | C20: =VLOOKUP(A20,Sales_Data!$A$1:$G$7,6,0) -> 15000 | D20: =B20*C20 -> 75000 | E20: =VLOOKUP(A20,Sales_Data!$A$1:$G$7,4,0) -> Mobile | F20: =VLOOKUP(E20,Product_Master!$A$1:$C$4,3,0) -> 12 | G20: =F20*D20/100 -> 9000 | H20: =G20+D20 -> 84000 | I20: =VLOOKUP(A20,Sales_Data!$A$1:$G$7,2,0) -> South | J20: =IF(Answer!B19>3,"High","Low") -> Low
A21: 305 | B21: =VLOOKUP(A21,Sales_Data!$A$1:$G$7,5,0) -> 4 | C21: =VLOOKUP(A21,Sales_Data!$A$1:$G$7,6,0) -> 15000 | D21: =B21*C21 -> 60000 | E21: =VLOOKUP(A21,Sales_Data!$A$1:$G$7,4,0) -> Mobile | F21: =VLOOKUP(E21,Product_Master!$A$1:$C$4,3,0) -> 12 | G21: =F21*D21/100 -> 7200 | H21: =G21+D21 -> 67200 | I21: =VLOOKUP(A21,Sales_Data!$A$1:$G$7,2,0) -> North | J21: =IF(Answer!B22>3,"High","Low") -> Low
A22: 303 | B22: =VLOOKUP(A22,Sales_Data!$A$1:$G$7,5,0) -> 3 | C22: =VLOOKUP(A22,Sales_Data!$A$1:$G$7,6,0) -> 18000 | D22: =B22*C22 -> 54000 | E22: =VLOOKUP(A22,Sales_Data!$A$1:$G$7,4,0) -> Tablet | F22: =VLOOKUP(E22,Product_Master!$A$1:$C$4,3,0) -> 12 | G22: =F22*D22/100 -> 6480 | H22: =G22+D22 -> 60480 | I22: =VLOOKUP(A22,Sales_Data!$A$1:$G$7,2,0) -> East | J22: =IF(Answer!B20>3,"High","Low") -> High
A23: 304 | B23: =VLOOKUP(A23,Sales_Data!$A$1:$G$7,5,0) -> 1 | C23: =VLOOKUP(A23,Sales_Data!$A$1:$G$7,6,0) -> 45000 | D23: =B23*C23 -> 45000 | E23: =VLOOKUP(A23,Sales_Data!$A$1:$G$7,4,0) -> Laptop | F23: =VLOOKUP(E23,Product_Master!$A$1:$C$4,3,0) -> 18 | G23: =F23*D23/100 -> 8100 | H23: =G23+D23 -> 53100 | I23: =VLOOKUP(A23,Sales_Data!$A$1:$G$7,2,0) -> West | J23: =IF(Answer!B21>3,"High","Low") -> High

Sheet Answer-2
A1: Student_ID | B1: Name | C1: Maths | D1: Statistics | E1: Excel | F1: Attendance_%
A2: 1 | B2: Rahul | C2: 78 | D2: 82 | E2: 85 | F2: 92
A3: 2 | B3: Sneha | C3: 88 | D3: 91 | E3: 90 | F3: 96
A4: 3 | B4: Arjun | C4: 65 | D4: 70 | E4: 72 | F4: 85
A5: 4 | B5: Pooja | C5: 92 | D5: 89 | E5: 94 | F5: 98
A6: 5 | B6: Vikas | C6: 55 | D6: 60 | E6: 58 | F6: 80
K8: Names | L8: Math
K9: Rahul | L9: =SUM(C2:E2)/3 -> 81.666667
K10: Sneha | L10: =SUM(C3:E3)/3 -> 89.666667
K11: Arjun | L11: =SUM(C4:E4)/3 -> 69
K12: Pooja | L12: =SUM(C5:E5)/3 -> 91.666667
K13: Vikas | L13: =SUM(C6:E6)/3 -> 57.666667
